[{"date":"2020-12-02T14:17","name":"porky-pig.jpg","size":103832,"mimetype":"image/jpeg","desc":"Porquinho"},{"date":"2020-12-02T14:29","name":"speedy.png","size":505127,"mimetype":"image/png","desc":"rapido"},{"date":"2020-12-02T14:31","name":"yosemite-sam.png","size":271582,"mimetype":"image/png","desc":"fabio"},{"date":"2020-12-02T15:19","name":"bugs-bunny.jpg","size":67755,"mimetype":"image/jpeg","desc":"joel"},{"date":"2020-12-03T11:35","name":"bugs-bunny.jpg","size":67755,"mimetype":"image/jpeg","desc":"1"},{"date":"2020-12-03T11:35","name":"coyotte.png","size":243362,"mimetype":"image/png","desc":"1"},{"date":"2020-12-03T11:36","name":"bugs-bunny.jpg","size":67755,"mimetype":"image/jpeg","desc":"joel"},{"date":"2020-12-03T11:36","name":"coyotte.png","size":243362,"mimetype":"image/png","desc":"joel2"},{"date":"2020-12-03T11:36","name":"tasmanian-devil.jpg","size":248401,"mimetype":"image/jpeg","desc":"t"},{"date":"2020-12-03T19:25","name":"yosemite-sam.png","size":271582,"mimetype":"image/png","desc":"aaa"},{"date":"2020-12-03T19:25","name":"tasmanian-devil.jpg","size":248401,"mimetype":"image/jpeg","desc":"bb"},{"date":"2020-12-03T19:25","name":"sylvester.png","size":240557,"mimetype":"image/png","desc":"cc"}]
